python_partiels/__init__.py
python_partiels/xml.py
python_partiels/templates/spectrogram.ptldoc
python_partiels-0.0.0.dist-info/licenses/LICENSE
python_partiels-0.0.0.dist-info/METADATA
python_partiels-0.0.0.dist-info/WHEEL
python_partiels-0.0.0.dist-info/top_level.txt
python_partiels-0.0.0.dist-info/RECORD
